addthree/__init__.py
addthree/add_three.py
addthree/pylint_test.py
tests/__init__.py
tests/test_add.py
addthree-0.1.1.dist-info/METADATA
addthree-0.1.1.dist-info/WHEEL
addthree-0.1.1.dist-info/top_level.txt
addthree-0.1.1.dist-info/RECORD
