Metadata-Version: 2.1
Name: addthree
Version: 0.1.1
Summary: Practice deploying to PyPI
Home-page: https://github.com/SeungUkLee/travis-practice
Author: test
Author-email: dltmddnr5@naver.com
License: MIT
Platform: UNKNOWN
Classifier: License :: OSI Approved :: MIT License
Classifier: Topic :: Utilities
Classifier: Development Status :: 1 - Planning
Classifier: Intended Audience :: Developers
